foreachiterator/__init__.py
foreachiterator/foreachiterator.py
tests/__init__.py
tests/test_foreachiterator.py
foreachiterator-1.2.0.dist-info/LICENSE
foreachiterator-1.2.0.dist-info/METADATA
foreachiterator-1.2.0.dist-info/WHEEL
foreachiterator-1.2.0.dist-info/entry_points.txt
foreachiterator-1.2.0.dist-info/top_level.txt
foreachiterator-1.2.0.dist-info/RECORD
