Metadata-Version: 2.1
Name: foreachiterator
Version: 1.2.0
Summary: A Python package for advanced iteration over iterables.
Home-page: https://github.com/Spraveen8-chary/foreachiterator
Author: S Praveen
Author-email: sarampentapraveen@example.com
Classifier: Programming Language :: Python :: 3
Classifier: License :: OSI Approved :: MIT License
Classifier: Operating System :: OS Independent
Requires-Python: >=3.6
License-File: LICENSE
Requires-Dist: pyfiglet
